pyqcoda/__init__.py
pyqcoda/core.py
pyqcoda-1.0.3.dist-info/LICENSE
pyqcoda-1.0.3.dist-info/METADATA
pyqcoda-1.0.3.dist-info/WHEEL
pyqcoda-1.0.3.dist-info/top_level.txt
pyqcoda-1.0.3.dist-info/RECORD
