Metadata-Version: 2.1
Name: pyqcoda
Version: 1.0.3
Summary: Temporal disaggregation of daily precipitation into hourly using Q-CODA.
Home-page: https://github.com/carloscorreag/pyqcoda
Author: Carlos Correa Guinea
Author-email: ccorreag@aemet.es
Classifier: Programming Language :: Python :: 3
Classifier: License :: OSI Approved :: MIT License
Classifier: Operating System :: OS Independent
Classifier: Topic :: Scientific/Engineering :: Hydrology
Classifier: Topic :: Scientific/Engineering :: Atmospheric Science
Requires-Python: >=3.7
License-File: LICENSE
Requires-Dist: pandas (>=1.2.4)
Requires-Dist: numpy (>=1.21.6)
Requires-Dist: scikit-learn (>=1.0.2)
